tap_stripe/__init__.py
tap_stripe/schemas/charges.json
tap_stripe/schemas/customers.json
tap_stripe/schemas/invoices.json
tap_stripe/schemas/plans.json
tap_stripe/schemas/subscriptions.json
tap_stripe/schemas/shared/coupon.json
tap_stripe/schemas/shared/discount.json
tap_stripe/schemas/shared/plan.json
tap_stripe/schemas/shared/source.json
tap_stripe/schemas/shared/subscription.json
tap_stripe/schemas/shared/subscription_item.json
tap_stripe-1.0.0.dist-info/METADATA
tap_stripe-1.0.0.dist-info/RECORD
tap_stripe-1.0.0.dist-info/WHEEL
tap_stripe-1.0.0.dist-info/entry_points.txt
tap_stripe-1.0.0.dist-info/top_level.txt
